sitkibex/__init__.py
sitkibex/__main__.py
sitkibex/_version.py
sitkibex/cli.py
sitkibex/globals.py
sitkibex/image_utilities.py
sitkibex/io.py
sitkibex/registration.py
sitkibex/registration_utilities.py
sitkibex/resample.py
sitkibex/xml_info.py
sitkibex-0.5.3.dist-info/licenses/LICENSE
sitkibex-0.5.3.dist-info/licenses/NOTICE
sitkibex-0.5.3.dist-info/METADATA
sitkibex-0.5.3.dist-info/WHEEL
sitkibex-0.5.3.dist-info/entry_points.txt
sitkibex-0.5.3.dist-info/top_level.txt
sitkibex-0.5.3.dist-info/RECORD
