Metadata-Version: 2.4
Name: sitkibex
Version: 0.5.3
Summary: Image registration for iterative fluorescence microscopy
Author-email: Bradley Lowekamp <bioinformatics@niaid.nih.gov>
Classifier: Programming Language :: Python :: 3
Classifier: License :: OSI Approved :: Apache Software License
Classifier: Operating System :: OS Independent
Requires-Python: >=3.8
License-File: LICENSE
License-File: NOTICE
Requires-Dist: SimpleITK>=2.0.0
Requires-Dist: click
Requires-Dist: numpy
Provides-Extra: zarr
Requires-Dist: zarr; extra == "zarr"
Provides-Extra: dev
Requires-Dist: pytest; extra == "dev"
Requires-Dist: flake8; extra == "dev"
Dynamic: license-file
